lp2ply/__init__.py
lp2ply/layup_search_funcs.py
lp2ply/lpfuncs.py
lp2ply-0.1.2.dist-info/LICENSE
lp2ply-0.1.2.dist-info/METADATA
lp2ply-0.1.2.dist-info/WHEEL
lp2ply-0.1.2.dist-info/top_level.txt
lp2ply-0.1.2.dist-info/RECORD
